pterobot/__init__.py
pterobot/main.py
pterobot-0.0.1.dist-info/METADATA
pterobot-0.0.1.dist-info/WHEEL
pterobot-0.0.1.dist-info/licenses/LICENSE
pterobot-0.0.1.dist-info/RECORD
