Metadata-Version: 2.1
Name: pterobot
Version: 0.0.1
Summary: A Discord bot for viewing and controlling Pterodactyl servers
Project-URL: Homepage, https://github.com/iamkubi/pterobot
Project-URL: Bug Tracker, https://github.com/iamkubi/pterobot/issues
Author-email: Ryan Kubiak <ryan@kubiq.io>
License-File: LICENSE
Classifier: License :: OSI Approved :: MIT License
Classifier: Operating System :: OS Independent
Classifier: Programming Language :: Python :: 3
Requires-Python: >=3.7
